fill_form.py
fill_form-0.0.1.dist-info/METADATA
fill_form-0.0.1.dist-info/WHEEL
fill_form-0.0.1.dist-info/top_level.txt
fill_form-0.0.1.dist-info/RECORD
