Metadata-Version: 2.1
Name: fill-form
Version: 0.0.1
Summary: fill the form....
Home-page: UNKNOWN
Author: UNKNOWN
Author-email: UNKNOWN
License: UNKNOWN
Platform: UNKNOWN
